aiokeydb/__init__.py
aiokeydb/backoff.py
aiokeydb/client.py
aiokeydb/cluster.py
aiokeydb/compat.py
aiokeydb/connection.py
aiokeydb/core.py
aiokeydb/crc.py
aiokeydb/exceptions.py
aiokeydb/lock.py
aiokeydb/queues.py
aiokeydb/retry.py
aiokeydb/sentinel.py
aiokeydb/typing.py
aiokeydb/version.py
aiokeydb/commands/__init__.py
aiokeydb/configs/__init__.py
aiokeydb/configs/core.py
aiokeydb/configs/worker.py
aiokeydb/serializers/__init__.py
aiokeydb/serializers/_json.py
aiokeydb/serializers/_msgpack.py
aiokeydb/serializers/_pickle.py
aiokeydb/types/__init__.py
aiokeydb/types/base.py
aiokeydb/types/cachify.py
aiokeydb/types/compat.py
aiokeydb/types/jobs.py
aiokeydb/types/serializer.py
aiokeydb/types/session.py
aiokeydb/types/static.py
aiokeydb/types/task_queue.py
aiokeydb/types/worker.py
aiokeydb/types/indexes/__init__.py
aiokeydb/types/indexes/base.py
aiokeydb/types/indexes/kdbdict.py
aiokeydb/types/indexes/utils.py
aiokeydb/utils/__init__.py
aiokeydb/utils/base.py
aiokeydb/utils/cron.py
aiokeydb/utils/helpers.py
aiokeydb/utils/lazy.py
aiokeydb/utils/logs.py
aiokeydb/utils/queue.py
aiokeydb/v1/__init__.py
aiokeydb/v1/backoff.py
aiokeydb/v1/cluster.py
aiokeydb/v1/compat.py
aiokeydb/v1/connection.py
aiokeydb/v1/core.py
aiokeydb/v1/crc.py
aiokeydb/v1/credentials.py
aiokeydb/v1/exceptions.py
aiokeydb/v1/lock.py
aiokeydb/v1/ocsp.py
aiokeydb/v1/parsers.py
aiokeydb/v1/retry.py
aiokeydb/v1/sentinel.py
aiokeydb/v1/typing.py
aiokeydb/v1/utils.py
aiokeydb/v1/asyncio/__init__.py
aiokeydb/v1/asyncio/client.py
aiokeydb/v1/asyncio/cluster.py
aiokeydb/v1/asyncio/connection.py
aiokeydb/v1/asyncio/core.py
aiokeydb/v1/asyncio/lock.py
aiokeydb/v1/asyncio/parser.py
aiokeydb/v1/asyncio/retry.py
aiokeydb/v1/asyncio/sentinel.py
aiokeydb/v1/asyncio/utils.py
aiokeydb/v1/client/__init__.py
aiokeydb/v1/client/config.py
aiokeydb/v1/client/core.py
aiokeydb/v1/client/meta.py
aiokeydb/v1/client/types.py
aiokeydb/v1/client/utils.py
aiokeydb/v1/client/schemas/__init__.py
aiokeydb-0.2.1.dist-info/METADATA
aiokeydb-0.2.1.dist-info/WHEEL
aiokeydb-0.2.1.dist-info/top_level.txt
aiokeydb-0.2.1.dist-info/RECORD
