Metadata-Version: 2.1
Name: aiokeydb
Version: 0.2.1
Summary: Python client for KeyDB database and key-value store
Home-page: https://github.com/trisongz/aiokeydb-py
Author: Tri Songz
Author-email: ts@growthengineai.com
License: MIT Style
Classifier: Intended Audience :: Developers
Classifier: License :: OSI Approved :: MIT License
Classifier: Programming Language :: Python :: 3.7
Classifier: Topic :: Software Development :: Libraries
Requires-Dist: deprecated >=1.2.3
Requires-Dist: packaging >=20.4
Requires-Dist: async-timeout >=4.0.2
Requires-Dist: lazyops >=0.2.61
Requires-Dist: redis <5.0.0
Requires-Dist: pydantic
Requires-Dist: anyio
Requires-Dist: croniter
Requires-Dist: tenacity
Requires-Dist: importlib-metadata >=1.0 ; python_version < "3.8"
Requires-Dist: typing-extensions ; python_version < "3.8"
Provides-Extra: hiredis
Requires-Dist: hiredis >=1.0.0 ; extra == 'hiredis'
Provides-Extra: ocsp
Requires-Dist: cryptography >=36.0.1 ; extra == 'ocsp'
Requires-Dist: pyopenssl ==20.0.1 ; extra == 'ocsp'
Requires-Dist: requests >=2.26.0 ; extra == 'ocsp'
